LICENSE
MANIFEST.in
README.rst
setup.py
django_orm2json.egg-info/PKG-INFO
django_orm2json.egg-info/SOURCES.txt
django_orm2json.egg-info/dependency_links.txt
django_orm2json.egg-info/top_level.txt
orm2json/__init__.py
orm2json/admin.py
orm2json/apps.py
orm2json/main.py
orm2json/models.py
orm2json/tests.py
orm2json/views.py
orm2json/migrations/__init__.py