Metadata-Version: 1.1
Name: django-orm2json
Version: 1.2.0
Summary: A library for converting ORM Django models to JSON format.
Home-page: https://github.com/MrEarnestWhim/orm2json
Author: Mr Earnest Whim
Author-email: 5494567@gmail.com
License: MIT License (MIT)
Platform: UNKNOWN
Classifier: Environment :: Web Environment
Classifier: Framework :: Django
Classifier: Framework :: Django :: 2.2
Classifier: Intended Audience :: Developers
Classifier: License :: OSI Approved :: MIT License
Classifier: Operating System :: OS Independent
Classifier: Programming Language :: Python
Classifier: Programming Language :: Python :: 3.5
Classifier: Programming Language :: Python :: 3.6
Classifier: Programming Language :: Python :: 3.7
Classifier: Topic :: Internet :: WWW/HTTP
Classifier: Topic :: Internet :: WWW/HTTP :: Dynamic Content
